comiks/__init__.py
comiks/authors.py
comiks/colors.py
comiks/config.py
comiks/config.toml
comiks/exceptions.py
comiks/model.py
comiks/provider/__init__.py
comiks/provider/base.py
comiks/provider/bitbucket.py
comiks/provider/github.py
comiks/provider/gitlab.py
comiks/run.py
comiks-1.0.0.dist-info/entry_points.txt
comiks-1.0.0.dist-info/LICENSE
comiks-1.0.0.dist-info/WHEEL
comiks-1.0.0.dist-info/METADATA
comiks-1.0.0.dist-info/RECORD
