Metadata-Version: 2.1
Name: comiks
Version: 1.0.0
Summary: Retrieve authors informations from commits.
Home-page: https://github.com/b0oml/Comiks
License: MIT
Author: b0oml
Requires-Python: >=3.7.2,<4.0.0
Classifier: License :: OSI Approved :: MIT License
Classifier: Programming Language :: Python :: 3
Classifier: Programming Language :: Python :: 3.10
Classifier: Programming Language :: Python :: 3.8
Classifier: Programming Language :: Python :: 3.9
Requires-Dist: GitPython (>=3.1.27,<4.0.0)
Requires-Dist: fastDamerauLevenshtein (>=1.0.7,<2.0.0)
Requires-Dist: requests (>=2.27.1,<3.0.0)
Requires-Dist: tabulate (>=0.8.9,<0.9.0)
Requires-Dist: toml (>=0.10.2,<0.11.0)
Project-URL: Repository, https://github.com/b0oml/Comiks
